damv1alertdaemon2025/__init__.py
damv1alertdaemon2025/discord_cleanup_daemon.py
damv1alertdaemon2025/discord_sender.py
damv1alertdaemon2025/grafana_url_generator.py
damv1alertdaemon2025/match_engine.py
damv1alertdaemon2025/polling.py
damv1alertdaemon2025/state_manager.py
damv1alertdaemon2025/steps.py
damv1alertdaemon2025-1.0.0.dist-info/LICENSE
damv1alertdaemon2025-1.0.0.dist-info/METADATA
damv1alertdaemon2025-1.0.0.dist-info/WHEEL
damv1alertdaemon2025-1.0.0.dist-info/top_level.txt
damv1alertdaemon2025-1.0.0.dist-info/RECORD
