Metadata-Version: 2.1
Name: damv1alertdaemon2025
Version: 1.0.0
Summary: development damv1alertdaemon2025 package
Home-page: UNKNOWN
Author: dhonyabumuhammad (Bekasi)
Author-email: <baba-rtw24133@tutamail.com>
License: UNKNOWN
Keywords: alertdaemon2025,discord_cleanup_daemon,discord_sender,polling-logs,grafana_url_generator
Platform: UNKNOWN
Classifier: Development Status :: 5 - Production/Stable
Classifier: Intended Audience :: Developers
Classifier: Operating System :: Unix
Classifier: Operating System :: MacOS :: MacOS X
Classifier: Operating System :: Microsoft :: Windows
Classifier: Programming Language :: Python :: 3
Classifier: Programming Language :: Python :: 3.7
Classifier: Programming Language :: Python :: 3.8
Classifier: Programming Language :: Python :: 3.9
Classifier: Programming Language :: Python :: 3.10
Classifier: Topic :: Software Development :: Debuggers
Classifier: License :: OSI Approved :: MIT License
Requires-Python: >=3.0
License-File: LICENSE
Requires-Dist: requests==2.32.4
Requires-Dist: python-dotenv==1.1.1
Requires-Dist: pytz==2025.2
Requires-Dist: Flask==3.1.1
Requires-Dist: discord.py==2.5.2
Requires-Dist: pyfiglet==1.0.4
